doltcli/__init__.py
doltcli/dolt.py
doltcli/types.py
doltcli/utils.py
lumicks_doltcli-0.2.1.dist-info/LICENSE
lumicks_doltcli-0.2.1.dist-info/METADATA
lumicks_doltcli-0.2.1.dist-info/WHEEL
lumicks_doltcli-0.2.1.dist-info/RECORD
