Metadata-Version: 2.1
Name: lumicks-doltcli
Version: 0.2.1
Summary: Slim Python interface for Dolt's CLI API.
Author: Max Hoffman
Author-email: max@dolthub.com
Requires-Python: >=3.8
Classifier: Programming Language :: Python
Classifier: Programming Language :: Python :: 3
Classifier: Programming Language :: Python :: 3.8
Classifier: Programming Language :: Python :: 3.9
Classifier: Programming Language :: Python :: 3.10
Classifier: Programming Language :: Python :: 3.11
